llama_index/tools/mcp/__init__.py
llama_index/tools/mcp/base.py
llama_index/tools/mcp/client.py
llama_index/tools/mcp/tool_spec_mixins.py
llama_index/tools/mcp/utils.py
llama_index_tools_mcp-0.4.4.dist-info/METADATA
llama_index_tools_mcp-0.4.4.dist-info/WHEEL
llama_index_tools_mcp-0.4.4.dist-info/licenses/LICENSE
llama_index_tools_mcp-0.4.4.dist-info/RECORD
