Metadata-Version: 2.4
Name: llama-index-tools-mcp
Version: 0.4.4
Summary: llama-index tools mcp integration
Author: Sebastian Kalisz
Author-email: Chojan Shang <psiace@outlook.com>
Maintainer: psiace
License-Expression: MIT
License-File: LICENSE
Keywords: mcp,tools
Requires-Python: <4.0,>=3.10
Requires-Dist: llama-index-core<0.15,>=0.13.0
Requires-Dist: mcp<2,>=1.9.1
Requires-Dist: pydantic<3,>=2.0.0
